MANIFEST.in
README.rst
requirements.txt
setup.cfg
setup.py
cloud_inquisitor/__init__.py
cloud_inquisitor/app.py
cloud_inquisitor/cli.py
cloud_inquisitor/config.py
cloud_inquisitor/constants.py
cloud_inquisitor/database.py
cloud_inquisitor/exceptions.py
cloud_inquisitor/json_utils.py
cloud_inquisitor/log.py
cloud_inquisitor/utils.py
cloud_inquisitor/wrappers.py
cloud_inquisitor/wsgi.py
cloud_inquisitor.egg-info/PKG-INFO
cloud_inquisitor.egg-info/SOURCES.txt
cloud_inquisitor.egg-info/dependency_links.txt
cloud_inquisitor.egg-info/entry_points.txt
cloud_inquisitor.egg-info/not-zip-safe
cloud_inquisitor.egg-info/requires.txt
cloud_inquisitor.egg-info/top_level.txt
cloud_inquisitor/data/migrations/README
cloud_inquisitor/data/migrations/alembic.ini
cloud_inquisitor/data/migrations/env.py
cloud_inquisitor/data/migrations/script.py.mako
cloud_inquisitor/data/migrations/versions/1edcdfbc7780_issueproperty_foreign_key.py
cloud_inquisitor/data/migrations/versions/3fca8951cd76_new_enforcements_table.py
cloud_inquisitor/data/migrations/versions/686dbbd19b95_initial_schema.py
cloud_inquisitor/data/migrations/versions/a2e49567641a_add_templates_table.py
cloud_inquisitor/data/migrations/versions/cfb0ed4cced9_new_accounts_table.py
cloud_inquisitor/data/migrations/versions/e2de0ea03287_update_account_contacts_to_new_format.py
cloud_inquisitor/data/migrations/versions/e445d703e60f_removing_partitions_adding_foreign_keys.py
cloud_inquisitor/data/templates/cloudtrail_s3_bucket_policy.json
cloud_inquisitor/data/templates/cloudtrail_sns_policy.json
cloud_inquisitor/data/templates/domain_hijacking.html
cloud_inquisitor/data/templates/domain_hijacking.txt
cloud_inquisitor/data/templates/required_tags_notice.html
cloud_inquisitor/data/templates/required_tags_notice.txt
cloud_inquisitor/data/templates/saml_settings.json
cloud_inquisitor/data/templates/syslog_format.json
cloud_inquisitor/data/templates/unattached_ebs_volume.html
cloud_inquisitor/data/templates/unattached_ebs_volume.txt
cloud_inquisitor/data/templates/vpc_flow_logs_iam_role_trust.json
cloud_inquisitor/data/templates/vpc_flow_logs_role_policy.json
cloud_inquisitor/plugins/__init__.py
cloud_inquisitor/plugins/commands/__init__.py
cloud_inquisitor/plugins/commands/auth.py
