Metadata-Version: 1.1
Name: cloud-inquisitor
Version: 2.2.0
Summary: Tool to enforce ownership and data security within cloud environments
Home-page: https://github.com/RiotGames/cloud-inquisitor
Author: Riot Games Security
Author-email: security@riotgames.com
License: Apache 2.0
Keywords: cloud security
Platform: UNKNOWN
Classifier: Development Status :: 4 - Beta
Classifier: Intended Audience :: System Administrators
Classifier: Intended Audience :: Information Technology
Classifier: License :: OSI Approved :: Apache Software License
Classifier: Programming Language :: Python :: 3.5
Classifier: Programming Language :: Python :: 3.6
Classifier: Framework :: Flask
Classifier: Operating System :: MacOS :: MacOS X
Classifier: Operating System :: POSIX :: Linux
Classifier: Operating System :: Unix
Classifier: Environment :: Console
Classifier: Natural Language :: English
Classifier: Topic :: Security
Classifier: Topic :: Utilities
